flask_rangerequest/__init__.py
flask_rangerequest/_request.py
flask_rangerequest/_utils.py
Flask_RangeRequest-0.0.2.dist-info/LICENSE-APACHE
Flask_RangeRequest-0.0.2.dist-info/LICENSE-MIT
Flask_RangeRequest-0.0.2.dist-info/METADATA
Flask_RangeRequest-0.0.2.dist-info/WHEEL
Flask_RangeRequest-0.0.2.dist-info/top_level.txt
Flask_RangeRequest-0.0.2.dist-info/RECORD
