Metadata-Version: 2.1
Name: Flask-RangeRequest
Version: 0.0.2
Summary: Range Requests for Flask
Home-page: https://github.com/heartsucker/flask-rangerequest
Author: heartsucker
Author-email: heartsucker@autistici.org
License: UNKNOWN
Platform: any
Classifier: Development Status :: 4 - Beta
Classifier: Intended Audience :: Developers
Classifier: License :: OSI Approved :: Apache Software License
Classifier: License :: OSI Approved :: MIT License
Classifier: Operating System :: OS Independent
Classifier: Programming Language :: Python :: 3 :: Only
Classifier: Programming Language :: Python :: 3.6
Classifier: Programming Language :: Python :: 3.7
Classifier: Programming Language :: Python :: 3.8
Classifier: Programming Language :: Python :: 3.9
Requires-Python: >=3.6
Requires-Dist: Flask (>=2)
